Workbook

Sheet Exec Summary
A1: SIMPLIMED
A2: in TEUR | C2: Y1 | D2: Y2 | E2: Y3
A3: Umsatz | C3: ='Umsatz Absatz Y 1-3'!O27 -> 878.9256 | D3: ='Umsatz Absatz Y 1-3'!AC27 -> 2952.7204 | E3: ='Umsatz Absatz Y 1-3'!AQ27 -> 4080.3902
A4: Wachstum y-o-y | D4: =+D3/C3-1 -> 2.3594656 | E4: =+E3/D3-1 -> 0.38190879
A5: Materialaufwand Op | C5: ='Kosten Y 1-3'!C12 -> 9.6 | D5: ='Kosten Y 1-3'!D12 -> 12 | E5: ='Kosten Y 1-3'!E12 -> 45
A6: % COGS von Umsatz | C6: =C5/C3 -> 0.010922426 | D6: =D5/D3 -> 0.0040640489 | E6: =E5/E3 -> 0.011028357
A7: Personal/Freelancer/SV Op | C7: ='Kosten Y 1-3'!C4+'Kosten Y 1-3'!C10+'Kosten Y 1-3'!C11 -> 483.801 | D7: ='Kosten Y 1-3'!D4+'Kosten Y 1-3'!D10+'Kosten Y 1-3'!D11 -> 684.6 | E7: ='Kosten Y 1-3'!E4+'Kosten Y 1-3'!E10+'Kosten Y 1-3'!E11 -> 968.58
A8: % von Umsatz | C8: =C7/C3 -> 0.55044591 | D8: =D7/D3 -> 0.23185399 | E8: =E7/E3 -> 0.23737436
A9: Marketing&Vertrieb Op | C9: ='Kosten Y 1-3'!C14 -> 21 | D9: ='Kosten Y 1-3'!D14 -> 80 | E9: ='Kosten Y 1-3'!E14 -> 227.5
A10: % von Umsatz | C10: =C9/C3 -> 0.023892807 | D10: =D9/D3 -> 0.02709366 | E10: =E9/E3 -> 0.055754471
A11: Raumkosten Op | C11: ='Kosten Y 1-3'!C13 -> 9.6 | D11: ='Kosten Y 1-3'!D13 -> 14.4 | E11: ='Kosten Y 1-3'!E13 -> 33
A12: % von Umsatz | C12: =C11/C3 -> 0.010922426 | D12: =D11/D3 -> 0.0048768587 | E12: =E11/E3 -> 0.0080874618
A13: Sonstige Kosten Op | C13: ='Kosten Y 1-3'!C15 -> 300 | D13: ='Kosten Y 1-3'!D15 -> 225 | E13: ='Kosten Y 1-3'!E15 -> 330
A14: % von Umsatz | C14: =C13/C3 -> 0.34132582 | D14: =D13/D3 -> 0.076200917 | E14: =E13/E3 -> 0.080874618
A15: EBITDA | C15: =C3-C5-C7-C9-C13 -> 64.5246 | D15: =D3-D5-D7-D9-D13 -> 1951.1204 | E15: =E3-E5-E7-E9-E13 -> 2509.3102
A16: EBITDA Margin | C16: =C15/C3 -> 0.07341304 | D16: =D15/D3 -> 0.66078738 | E16: =E15/E3 -> 0.6149682
A17: Entwicklungskosten | C17: ='Kosten Y 1-3'!C32 -> 259.02 | D17: ='Kosten Y 1-3'!D32 -> 499.14 | E17: ='Kosten Y 1-3'!E32 -> 735.96
A18: Abschreibungen | C18: ='Kosten Y 1-3'!C34 -> 6 | D18: ='Kosten Y 1-3'!D34 -> 42 | E18: ='Kosten Y 1-3'!E34 -> 42
A19: Zinsen/Erträge und sonst. Aufwand | G19: nicht berücksichtigt
A20: Steuern | D20: =(D15-D17+D18+C21)*0.28 -> 363.85579 | E20: =(E15-E17+E18)*0.28 -> 508.29806
A21: Earnings | C21: =C15-C17 -> -194.4954 | D21: =D15-D17 -> 1451.9804 | E21: =E15-E17 -> 1773.3502
A22: EBT Margin | C22: =C21/C3 -> -0.22128767 | D22: =D21/D3 -> 0.49174327 | E22: =E21/E3 -> 0.43460309
A24: Kosten Gesamt (inkl. Abschreibungen) | C24: ='Kosten Y 1-3'!C36 -> 1089.021 | D24: ='Kosten Y 1-3'!D36 -> 1557.14 | E24: ='Kosten Y 1-3'!E36 -> 2382.04

Sheet Umsatz Absatz Y 1-3
A1: Jahr 1 Entwicklungsjahr | P1: Jahr 2 - Roll Out | AD1: Jahr 3 - Expansion
C2: Monat 1 | D2: Monat 2 | E2: Monat 3 | F2: Monat 4 | G2: Monat 5 | H2: Monat 6 | I2: Monat 7 | J2: Monat 8 | K2: Monat 9 | L2: Monat 10 | M2: Monat 11 | N2: Monat 12 | O2: FY1 | Q2: Monat 1 | R2: Monat 2 | S2: Monat 3 | T2: Monat 4 | U2: Monat 5 | V2: Monat 6 | W2: Monat 7 | X2: Monat 8 | Y2: Monat 9 | Z2: Monat 10 | AA2: Monat 11 | AB2: Monat 12 | AC2: FY2 | AE2: Monat 1 | AF2: Monat 2 | AG2: Monat 3 | AH2: Monat 4 | AI2: Monat 5 | AJ2: Monat 6 | AK2: Monat 7 | AL2: Monat 8 | AM2: Monat 9 | AN2: Monat 10 | AO2: Monat 11 | AP2: Monat 12 | AQ2: FY3
A3: Absatz
A4: Basis | C4: =SUM(C5:C6) -> 4012 | D4: =SUM(D5:D6) -> 4024 | E4: =SUM(E5:E6) -> 4036 | F4: =SUM(F5:F6) -> 4048 | G4: =SUM(G5:G6) -> 4060 | H4: =SUM(H5:H6) -> 4072 | I4: =SUM(I5:I6) -> 4084 | J4: =SUM(J5:J6) -> 4096 | ... N4: =SUM(N5:N6) -> 4144 | O4: =N4 -> 4144 | Q4: =SUM(Q5:Q6) -> 3169 | R4: =Q4+R6-Q6 -> 3194 | S4: =R4+S6-R6 -> 3219 | T4: =S4+T6-S6 -> 3244 | U4: =T4+U6-T6 -> 3269 | V4: =U4+V6-U6 -> 3294 | W4: =V4+W6-V6 -> 3319 | X4: =W4+X6-W6 -> 3344 | Y4: =X4+Y6-X6 -> 3369 | ... AB4: =AA4+AB6-AA6 -> 3444 | AC4: =AB4 -> 3444 | AE4: =AB4+AE6-AB6 -> 3544 | AF4: =AE4+AF6-AE6 -> 3644 | AG4: =AF4+AG6-AF6 -> 3744 | AH4: =AG4+AH6-AG6 -> 3844 | AI4: =AH4+AI6-AH6 -> 3944 | AJ4: =AI4+AJ6-AI6 -> 4044 | AK4: =AJ4+AK6-AJ6 -> 4144 | AL4: =AK4+AL6-AK6 -> 4244 | AM4: =AL4+AM6-AL6 -> 4344 | ... AP4: =AO4+AP6-AO6 -> 4644 | AQ4: =AP4 -> 4644
A5: davon Altkunden | C5: 4000 | D5: 4000 | E5: 4000 | F5: 4000 | G5: 4000 | H5: 4000 | I5: 4000 | J5: 4000 | K5: 4000 | L5: 4000 | M5: 4000 | N5: 4000 | O5: =N5 -> 4000 | Q5: =$B$31-($B$31*$B$32) -> 3000 | R5: =$B$31-($B$31*$B$32) -> 3000 | S5: =$B$31-($B$31*$B$32) -> 3000 | T5: =$B$31-($B$31*$B$32) -> 3000 | U5: =$B$31-($B$31*$B$32) -> 3000 | V5: =$B$31-($B$31*$B$32) -> 3000 | W5: =$B$31-($B$31*$B$32) -> 3000 | X5: =$B$31-($B$31*$B$32) -> 3000 | ... AB5: =$B$31-($B$31*$B$32) -> 3000 | AC5: =AB5 -> 3000 | AE5: =$B$31-($B$31*$B$32)+50 -> 3050 | AF5: =AE5+50 -> 3100 | AG5: =AF5+50 -> 3150 | AH5: =AG5+50 -> 3200 | AI5: =AH5+50 -> 3250 | AJ5: =AI5+50 -> 3300 | AK5: =AJ5+50 -> 3350 | AL5: =AK5+50 -> 3400 | AM5: =AL5+50 -> 3450 | ... AP5: =AO5+50 -> 3600 | AQ5: =AP5 -> 3600
A6: davon Neukunden | C6: 12 | D6: 24 | E6: 36 | F6: 48 | G6: 60 | H6: 72 | I6: 84 | J6: 96 | K6: 108 | L6: 120 | M6: 132 | N6: 144 | O6: =N6 -> 144 | Q6: =N6+25 -> 169 | R6: =Q6+25 -> 194 | S6: =R6+25 -> 219 | T6: =S6+25 -> 244 | U6: =T6+25 -> 269 | V6: =U6+25 -> 294 | W6: =V6+25 -> 319 | X6: =W6+25 -> 344 | Y6: =X6+25 -> 369 | ... AB6: =AA6+25 -> 444 | AC6: =AB6 -> 444 | AE6: =AB6+100 -> 544 | AF6: =AE6+100 -> 644 | AG6: =AF6+100 -> 744 | AH6: =AG6+100 -> 844 | AI6: =AH6+100 -> 944 | AJ6: =AI6+100 -> 1044 | AK6: =AJ6+100 -> 1144 | AL6: =AK6+100 -> 1244 | AM6: =AL6+100 -> 1344 | ... AP6: =AO6+100 -> 1644 | AQ6: =AP6 -> 1644
A7: Zusatzmodule | O7: =N7 -> 0 | Q7: =SUM(Q8:Q10) -> 59.41875 | R7: =SUM(R8:R10) -> 119.30625 | S7: =SUM(S8:S10) -> 179.6625 | T7: =SUM(T8:T10) -> 240.4875 | U7: =SUM(U8:U10) -> 301.78125 | V7: =SUM(V8:V10) -> 363.54375 | W7: =SUM(W8:W10) -> 425.775 | X7: =SUM(X8:X10) -> 488.475 | ... AB7: =SUM(AB8:AB10) -> 743.9625 | AC7: =AB7 -> 743.9625 | AE7: =SUM(AE8:AE10) -> 862.09583 | AF7: =SUM(AF8:AF10) -> 983.5625 | AG7: =SUM(AG8:AG10) -> 1108.3625 | AH7: =SUM(AH8:AH10) -> 1236.4958 | AI7: =SUM(AI8:AI10) -> 1367.9625 | AJ7: =SUM(AJ8:AJ10) -> 1502.7625 | AK7: =SUM(AK8:AK10) -> 1640.8958 | AL7: =SUM(AL8:AL10) -> 1782.3625 | ... AP7: =SUM(AP8:AP10) -> 2381.5625 | AQ7: =AP7 -> 2381.5625
A8: davon Fakturierung 2 | O8: =N8 -> 0 | Q8: =Q$4*$D40 -> 39.6125 | R8: =R$4*$D40+Q8 -> 79.5375 | S8: =S$4*$D40+R8 -> 119.775 | T8: =T$4*$D40+S8 -> 160.325 | U8: =U$4*$D40+T8 -> 201.1875 | V8: =V$4*$D40+U8 -> 242.3625 | W8: =W$4*$D40+V8 -> 283.85 | X8: =X$4*$D40+W8 -> 325.65 | Y8: =Y$4*$D40+X8 -> 367.7625 | ... AB8: =AB$4*$D40+AA8 -> 495.975 | AC8: =AB8 -> 495.975 | AE8: =AE$4*$E40+AB8 -> 569.80833 | AF8: =AF$4*$E40+AE8 -> 645.725 | AG8: =AG$4*$E40+AF8 -> 723.725 | AH8: =AH$4*$E40+AG8 -> 803.80833 | AI8: =AI$4*$E40+AH8 -> 885.975 | AJ8: =AJ$4*$E40+AI8 -> 970.225 | AK8: =AK$4*$E40+AJ8 -> 1056.5583 | AL8: =AL$4*$E40+AK8 -> 1144.975 | AM8: =AM$4*$E40+AL8 -> 1235.475 | ... AP8: =AP$4*$E40+AO8 -> 1519.475 | AQ8: =AP8 -> 1519.475
A9: davon Terminbuchung | O9: =N9 -> 0 | Q9: =Q$4*$D41 -> 13.204167 | R9: =R$4*$D41+Q9 -> 26.5125 | S9: =S$4*$D41+R9 -> 39.925 | T9: =T$4*$D41+S9 -> 53.441667 | U9: =U$4*$D41+T9 -> 67.0625 | V9: =V$4*$D41+U9 -> 80.7875 | W9: =W$4*$D41+V9 -> 94.616667 | X9: =X$4*$D41+W9 -> 108.55 | Y9: =Y$4*$D41+X9 -> 122.5875 | ... AB9: =AB$4*$D41+AA9 -> 165.325 | AC9: =AB9 -> 165.325 | AE9: =AE$4*$E41+AB9 -> 194.85833 | AF9: =AF$4*$E41+AE9 -> 225.225 | AG9: =AG$4*$E41+AF9 -> 256.425 | AH9: =AH$4*$E41+AG9 -> 288.45833 | AI9: =AI$4*$E41+AH9 -> 321.325 | AJ9: =AJ$4*$E41+AI9 -> 355.025 | AK9: =AK$4*$E41+AJ9 -> 389.55833 | AL9: =AL$4*$E41+AK9 -> 424.925 | AM9: =AM$4*$E41+AL9 -> 461.125 | ... AP9: =AP$4*$E41+AO9 -> 574.725 | AQ9: =AP9 -> 574.725
A10: davon NutriShop24 | O10: =N10 -> 0 | Q10: =Q$4*$D42 -> 6.6020833 | R10: =R$4*$D42+Q10 -> 13.25625 | S10: =S$4*$D42+R10 -> 19.9625 | T10: =T$4*$D42+S10 -> 26.720833 | U10: =U$4*$D42+T10 -> 33.53125 | V10: =V$4*$D42+U10 -> 40.39375 | W10: =W$4*$D42+V10 -> 47.308333 | X10: =X$4*$D42+W10 -> 54.275 | Y10: =Y$4*$D42+X10 -> 61.29375 | ... AB10: =AB$4*$D42+AA10 -> 82.6625 | AC10: =AB10 -> 82.6625 | AE10: =AE$4*$E42+AB10 -> 97.429167 | AF10: =AF$4*$E42+AE10 -> 112.6125 | AG10: =AG$4*$E42+AF10 -> 128.2125 | AH10: =AH$4*$E42+AG10 -> 144.22917 | AI10: =AI$4*$E42+AH10 -> 160.6625 | AJ10: =AJ$4*$E42+AI10 -> 177.5125 | AK10: =AK$4*$E42+AJ10 -> 194.77917 | AL10: =AL$4*$E42+AK10 -> 212.4625 | AM10: =AM$4*$E42+AL10 -> 230.5625 | ... AP10: =AP$4*$E42+AO10 -> 287.3625 | AQ10: =AP10 -> 287.3625
A11: weitere | AE11: =AE$4*$E43 -> 14.766667 | AF11: =AF$4*$E43+AE11 -> 29.95 | AG11: =AG$4*$E43+AF11 -> 45.55 | AH11: =AH$4*$E43+AG11 -> 61.566667 | AI11: =AI$4*$E43+AH11 -> 78 | AJ11: =AJ$4*$E43+AI11 -> 94.85 | AK11: =AK$4*$E43+AJ11 -> 112.11667 | AL11: =AL$4*$E43+AK11 -> 129.8 | AM11: =AM$4*$E43+AL11 -> 147.9 | ... AP11: =AP$4*$E43+AO11 -> 204.7 | AQ11: =AP11 -> 204.7
A12: Umsatz in TEUR | B12: Preis p.M. | P12: Preis p.M. | AD12: Preis p.M.
A13: Basis | C13: =C14+C18 -> 69.1452 | D13: =D14+D18 -> 69.8904 | E13: =E14+E18 -> 70.6356 | F13: =F14+F18 -> 71.3808 | G13: =G14+G18 -> 72.126 | H13: =H14+H18 -> 72.8712 | I13: =I14+I18 -> 73.6164 | J13: =J14+J18 -> 74.3616 | ... N13: =N14+N18 -> 77.3424 | O13: =SUM(C13:N13) -> 878.9256 | Q13: =Q14+Q18 -> 228.168 | R13: =R14+R18 -> 229.968 | S13: =S14+S18 -> 231.768 | T13: =T14+T18 -> 233.568 | U13: =U14+U18 -> 235.368 | V13: =V14+V18 -> 237.168 | W13: =W14+W18 -> 238.968 | X13: =X14+X18 -> 240.768 | ... AB13: =AB14+AB18 -> 247.968 | AC13: =SUM(Q13:AB13) -> 2856.816 | AE13: =AE14+AE18 -> 258.768 | AF13: =AF14+AF18 -> 269.568 | AG13: =AG14+AG18 -> 280.368 | AH13: =AH14+AH18 -> 291.168 | AI13: =AI14+AI18 -> 301.968 | AJ13: =AJ14+AJ18 -> 312.768 | AK13: =AK14+AK18 -> 323.568 | AL13: =AL14+AL18 -> 334.368 | ... AP13: =AP14+AP18 -> 377.568 | AQ13: =SUM(AE13:AP13) -> 3818.016
A14: davon Altkunden | C14: =C15+C16 -> 68.4 | D14: =D15+D16 -> 68.4 | E14: =E15+E16 -> 68.4 | F14: =F15+F16 -> 68.4 | G14: =G15+G16 -> 68.4 | H14: =H15+H16 -> 68.4 | I14: =I15+I16 -> 68.4 | J14: =J15+J16 -> 68.4 | ... O14: =O15+O16 -> 820.8 | Q14: =Q15+Q16 -> 216 | R14: =R15+R16 -> 216 | S14: =S15+S16 -> 216 | T14: =T15+T16 -> 216 | U14: =U15+U16 -> 216 | V14: =V15+V16 -> 216 | W14: =W15+W16 -> 216 | X14: =X15+X16 -> 216 | ... AC14: =AC15+AC16 -> 2592 | AE14: =AE15+AE16 -> 219.6 | AF14: =AF15+AF16 -> 223.2 | AG14: =AG15+AG16 -> 226.8 | AH14: =AH15+AH16 -> 230.4 | AI14: =AI15+AI16 -> 234 | AJ14: =AJ15+AJ16 -> 237.6 | AK14: =AK15+AK16 -> 241.2 | AL14: =AL15+AL16 -> 244.8 | ... AQ14: =AQ15+AQ16 -> 2872.8
A15: davon Teamlizenzen | C15: =C5*$B34*$B15/1000 -> 0 | D15: =D5*$B34*$B15/1000 -> 0 | E15: =E5*$B34*$B15/1000 -> 0 | F15: =F5*$B34*$B15/1000 -> 0 | G15: =G5*$B34*$B15/1000 -> 0 | H15: =H5*$B34*$B15/1000 -> 0 | I15: =I5*$B34*$B15/1000 -> 0 | J15: =J5*$B34*$B15/1000 -> 0 | ... N15: =N5*$B34*$B15/1000 -> 0 | O15: =SUM(C15:N15) -> 0 | P15: 99 | Q15: =Q5*$B34*$P15/1000 -> 29.7 | R15: =R5*$B34*$P15/1000 -> 29.7 | S15: =S5*$B34*$P15/1000 -> 29.7 | T15: =T5*$B34*$P15/1000 -> 29.7 | U15: =U5*$B34*$P15/1000 -> 29.7 | V15: =V5*$B34*$P15/1000 -> 29.7 | W15: =W5*$B34*$P15/1000 -> 29.7 | X15: =X5*$B34*$P15/1000 -> 29.7 | ... AB15: =AB5*$B34*$P15/1000 -> 29.7 | AC15: =SUM(Q15:AB15) -> 356.4 | AD15: 99 | AE15: =AE5*$B34*$AD15/1000 -> 30.195 | AF15: =AF5*$B34*$AD15/1000 -> 30.69 | AG15: =AG5*$B34*$AD15/1000 -> 31.185 | AH15: =AH5*$B34*$AD15/1000 -> 31.68 | AI15: =AI5*$B34*$AD15/1000 -> 32.175 | AJ15: =AJ5*$B34*$AD15/1000 -> 32.67 | AK15: =AK5*$B34*$AD15/1000 -> 33.165 | AL15: =AL5*$B34*$AD15/1000 -> 33.66 | ... AP15: =AP5*$B34*$AD15/1000 -> 35.64 | AQ15: =SUM(AE15:AP15) -> 395.01
A16: davon Einzellizenzen | B16: 19 | C16: =C5*$B35*$B16/1000 -> 68.4 | D16: =D5*$B35*$B16/1000 -> 68.4 | E16: =E5*$B35*$B16/1000 -> 68.4 | F16: =F5*$B35*$B16/1000 -> 68.4 | G16: =G5*$B35*$B16/1000 -> 68.4 | H16: =H5*$B35*$B16/1000 -> 68.4 | I16: =I5*$B35*$B16/1000 -> 68.4 | J16: =J5*$B35*$B16/1000 -> 68.4 | ... N16: =N5*$B35*$B16/1000 -> 68.4 | O16: =SUM(C16:N16) -> 820.8 | P16: 69 | Q16: =Q5*$B35*$P16/1000 -> 186.3 | R16: =R5*$B35*$P16/1000 -> 186.3 | S16: =S5*$B35*$P16/1000 -> 186.3 | T16: =T5*$B35*$P16/1000 -> 186.3 | U16: =U5*$B35*$P16/1000 -> 186.3 | V16: =V5*$B35*$P16/1000 -> 186.3 | W16: =W5*$B35*$P16/1000 -> 186.3 | X16: =X5*$B35*$P16/1000 -> 186.3 | ... AB16: =AB5*$B35*$P16/1000 -> 186.3 | AC16: =SUM(Q16:AB16) -> 2235.6 | AD16: 69 | AE16: =AE5*$B35*$AD16/1000 -> 189.405 | AF16: =AF5*$B35*$AD16/1000 -> 192.51 | AG16: =AG5*$B35*$AD16/1000 -> 195.615 | AH16: =AH5*$B35*$AD16/1000 -> 198.72 | AI16: =AI5*$B35*$AD16/1000 -> 201.825 | AJ16: =AJ5*$B35*$AD16/1000 -> 204.93 | AK16: =AK5*$B35*$AD16/1000 -> 208.035 | AL16: =AL5*$B35*$AD16/1000 -> 211.14 | ... AP16: =AP5*$B35*$AD16/1000 -> 223.56 | AQ16: =SUM(AE16:AP16) -> 2477.79
A18: davon Neukunden | C18: =SUM(C19:C20) -> 0.7452 | D18: =SUM(D19:D20) -> 1.4904 | E18: =SUM(E19:E20) -> 2.2356 | F18: =SUM(F19:F20) -> 2.9808 | G18: =SUM(G19:G20) -> 3.726 | H18: =SUM(H19:H20) -> 4.4712 | I18: =SUM(I19:I20) -> 5.2164 | J18: =SUM(J19:J20) -> 5.9616 | ... O18: =SUM(O19:O20) -> 58.1256 | Q18: =SUM(Q19:Q20) -> 12.168 | R18: =SUM(R19:R20) -> 13.968 | S18: =SUM(S19:S20) -> 15.768 | T18: =SUM(T19:T20) -> 17.568 | U18: =SUM(U19:U20) -> 19.368 | V18: =SUM(V19:V20) -> 21.168 | W18: =SUM(W19:W20) -> 22.968 | X18: =SUM(X19:X20) -> 24.768 | ... AC18: =SUM(AC19:AC20) -> 264.816 | AE18: =SUM(AE19:AE20) -> 39.168 | AF18: =SUM(AF19:AF20) -> 46.368 | AG18: =SUM(AG19:AG20) -> 53.568 | AH18: =SUM(AH19:AH20) -> 60.768 | AI18: =SUM(AI19:AI20) -> 67.968 | AJ18: =SUM(AJ19:AJ20) -> 75.168 | AK18: =SUM(AK19:AK20) -> 82.368 | AL18: =SUM(AL19:AL20) -> 89.568 | ... AQ18: =SUM(AQ19:AQ20) -> 945.216
A19: davon Teamlizenzen | C19: =C6*$B$34*$B$19/1000 -> 0 | D19: =D6*$B$34*$B$19/1000 -> 0 | E19: =E6*$B$34*$B$19/1000 -> 0 | F19: =F6*$B$34*$B$19/1000 -> 0 | G19: =G6*$B$34*$B$19/1000 -> 0 | H19: =H6*$B$34*$B$19/1000 -> 0 | I19: =I6*$B$34*$B$19/1000 -> 0 | J19: =J6*$B$34*$B$19/1000 -> 0 | ... N19: =N6*$B$34*$B$19/1000 -> 0 | O19: =SUM(C19:N19) -> 0 | P19: 99 | Q19: =Q6*$B$34*$P$19/1000 -> 1.6731 | R19: =R6*$B$34*$P$19/1000 -> 1.9206 | S19: =S6*$B$34*$P$19/1000 -> 2.1681 | T19: =T6*$B$34*$P$19/1000 -> 2.4156 | U19: =U6*$B$34*$P$19/1000 -> 2.6631 | V19: =V6*$B$34*$P$19/1000 -> 2.9106 | W19: =W6*$B$34*$P$19/1000 -> 3.1581 | X19: =X6*$B$34*$P$19/1000 -> 3.4056 | ... AB19: =AB6*$B$34*$P$19/1000 -> 4.3956 | AC19: =SUM(Q19:AB19) -> 36.4122 | AD19: 99 | AE19: =AE6*$B$34*$AD$19/1000 -> 5.3856 | AF19: =AF6*$B$34*$AD$19/1000 -> 6.3756 | AG19: =AG6*$B$34*$AD$19/1000 -> 7.3656 | AH19: =AH6*$B$34*$AD$19/1000 -> 8.3556 | AI19: =AI6*$B$34*$AD$19/1000 -> 9.3456 | AJ19: =AJ6*$B$34*$AD$19/1000 -> 10.3356 | AK19: =AK6*$B$34*$AD$19/1000 -> 11.3256 | AL19: =AL6*$B$34*$AD$19/1000 -> 12.3156 | ... AP19: =AP6*$B$34*$AD$19/1000 -> 16.2756 | AQ19: =SUM(AE19:AP19) -> 129.9672
A20: davon Einzellizenzen | B20: 69 | C20: =C6*$B$35*$B$20/1000 -> 0.7452 | D20: =D6*$B$35*$B$20/1000 -> 1.4904 | E20: =E6*$B$35*$B$20/1000 -> 2.2356 | F20: =F6*$B$35*$B$20/1000 -> 2.9808 | G20: =G6*$B$35*$B$20/1000 -> 3.726 | H20: =H6*$B$35*$B$20/1000 -> 4.4712 | I20: =I6*$B$35*$B$20/1000 -> 5.2164 | J20: =J6*$B$35*$B$20/1000 -> 5.9616 | ... N20: =N6*$B$35*$B$20/1000 -> 8.9424 | O20: =SUM(C20:N20) -> 58.1256 | P20: 69 | Q20: =Q6*$B$35*$P$20/1000 -> 10.4949 | R20: =R6*$B$35*$P$20/1000 -> 12.0474 | S20: =S6*$B$35*$P$20/1000 -> 13.5999 | T20: =T6*$B$35*$P$20/1000 -> 15.1524 | U20: =U6*$B$35*$P$20/1000 -> 16.7049 | V20: =V6*$B$35*$P$20/1000 -> 18.2574 | W20: =W6*$B$35*$P$20/1000 -> 19.8099 | X20: =X6*$B$35*$P$20/1000 -> 21.3624 | ... AB20: =AB6*$B$35*$P$20/1000 -> 27.5724 | AC20: =SUM(Q20:AB20) -> 228.4038 | AD20: 69 | AE20: =AE6*$B$35*$AD$20/1000 -> 33.7824 | AF20: =AF6*$B$35*$AD$20/1000 -> 39.9924 | AG20: =AG6*$B$35*$AD$20/1000 -> 46.2024 | AH20: =AH6*$B$35*$AD$20/1000 -> 52.4124 | AI20: =AI6*$B$35*$AD$20/1000 -> 58.6224 | AJ20: =AJ6*$B$35*$AD$20/1000 -> 64.8324 | AK20: =AK6*$B$35*$AD$20/1000 -> 71.0424 | AL20: =AL6*$B$35*$AD$20/1000 -> 77.2524 | ... AP20: =AP6*$B$35*$AD$20/1000 -> 102.0924 | AQ20: =SUM(AE20:AP20) -> 815.2488
A22: Zusatzmodule | Q22: =SUM(Q23:Q25) -> 1.1949771 | R22: =SUM(R23:R25) -> 2.3993812 | S22: =SUM(S23:S25) -> 3.6132125 | T22: =SUM(T23:T25) -> 4.8364708 | U22: =SUM(U23:U25) -> 6.0691562 | V22: =SUM(V23:V25) -> 7.3112687 | W22: =SUM(W23:W25) -> 8.5628083 | X22: =SUM(X23:X25) -> 9.823775 | ... AB22: =SUM(AB23:AB25) -> 14.961913 | AC22: =SUM(Q22:AB22) -> 95.904358 | AE22: =SUM(AE23:AE25) -> 11.656029 | AF22: =SUM(AF23:AF25) -> 13.356562 | AG22: =SUM(AG23:AG25) -> 15.103763 | AH22: =SUM(AH23:AH25) -> 16.897629 | AI22: =SUM(AI23:AI25) -> 18.738163 | AJ22: =SUM(AJ23:AJ25) -> 20.625363 | AK22: =SUM(AK23:AK25) -> 22.559229 | AL22: =SUM(AL23:AL25) -> 24.539763 | ... AP22: =SUM(AP23:AP25) -> 32.928563 | AQ22: =SUM(AE22:AP22) -> 262.37422
A23: davon Fakturierung 2 | P23: 19 | Q23: =Q8*$P23/1000 -> 0.7526375 | R23: =R8*$P23/1000 -> 1.5112125 | S23: =S8*$P23/1000 -> 2.275725 | T23: =T8*$P23/1000 -> 3.046175 | U23: =U8*$P23/1000 -> 3.8225625 | V23: =V8*$P23/1000 -> 4.6048875 | W23: =W8*$P23/1000 -> 5.39315 | X23: =X8*$P23/1000 -> 6.18735 | ... AB23: =AB8*$P23/1000 -> 9.423525 | AC23: =SUM(Q23:AB23) -> 60.40385 | AD23: 9 | AE23: =AE8*$AD23/1000 -> 5.128275 | AF23: =AF8*$AD23/1000 -> 5.811525 | AG23: =AG8*$AD23/1000 -> 6.513525 | AH23: =AH8*$AD23/1000 -> 7.234275 | AI23: =AI8*$AD23/1000 -> 7.973775 | AJ23: =AJ8*$AD23/1000 -> 8.732025 | AK23: =AK8*$AD23/1000 -> 9.509025 | AL23: =AL8*$AD23/1000 -> 10.304775 | ... AP23: =AP8*$AD23/1000 -> 13.675275 | AQ23: =SUM(AE23:AP23) -> 110.7588
A24: davon Terminbuchung | P24: 19 | Q24: =Q9*$P24/1000 -> 0.25087917 | R24: =R9*$P24/1000 -> 0.5037375 | S24: =S9*$P24/1000 -> 0.758575 | T24: =T9*$P24/1000 -> 1.0153917 | U24: =U9*$P24/1000 -> 1.2741875 | V24: =V9*$P24/1000 -> 1.5349625 | W24: =W9*$P24/1000 -> 1.7977167 | X24: =X9*$P24/1000 -> 2.06245 | ... AB24: =AB9*$P24/1000 -> 3.141175 | AD24: 19 | AE24: =AE9*$AD24/1000 -> 3.7023083 | AF24: =AF9*$AD24/1000 -> 4.279275 | AG24: =AG9*$AD24/1000 -> 4.872075 | AH24: =AH9*$AD24/1000 -> 5.4807083 | AI24: =AI9*$AD24/1000 -> 6.105175 | AJ24: =AJ9*$AD24/1000 -> 6.745475 | AK24: =AK9*$AD24/1000 -> 7.4016083 | AL24: =AL9*$AD24/1000 -> 8.073575 | ... AP24: =AP9*$AD24/1000 -> 10.919775
A25: davon NutriShop | P25: 29 | Q25: =Q10*$P25/1000 -> 0.19146042 | R25: =R10*$P25/1000 -> 0.38443125 | S25: =S10*$P25/1000 -> 0.5789125 | T25: =T10*$P25/1000 -> 0.77490417 | U25: =U10*$P25/1000 -> 0.97240625 | V25: =V10*$P25/1000 -> 1.1714187 | W25: =W10*$P25/1000 -> 1.3719417 | X25: =X10*$P25/1000 -> 1.573975 | ... AB25: =AB10*$P25/1000 -> 2.3972125 | AC25: =SUM(Q25:AB25) -> 15.365892 | AD25: 29 | AE25: =AE10*$AD25/1000 -> 2.8254458 | AF25: =AF10*$AD25/1000 -> 3.2657625 | AG25: =AG10*$AD25/1000 -> 3.7181625 | AH25: =AH10*$AD25/1000 -> 4.1826458 | AI25: =AI10*$AD25/1000 -> 4.6592125 | AJ25: =AJ10*$AD25/1000 -> 5.1478625 | AK25: =AK10*$AD25/1000 -> 5.6485958 | AL25: =AL10*$AD25/1000 -> 6.1614125 | ... AP25: =AP10*$AD25/1000 -> 8.3335125 | AQ25: =SUM(AE25:AP25) -> 65.624583
A26: davon weitere | P26: 15 | AD26: 15
A27: Gesamtleistung | C27: =C13+C22 -> 69.1452 | D27: =D13+D22 -> 69.8904 | E27: =E13+E22 -> 70.6356 | F27: =F13+F22 -> 71.3808 | G27: =G13+G22 -> 72.126 | H27: =H13+H22 -> 72.8712 | I27: =I13+I22 -> 73.6164 | J27: =J13+J22 -> 74.3616 | ... N27: =N13+N22 -> 77.3424 | O27: =SUM(C27:N27) -> 878.9256 | Q27: =Q13+Q22 -> 229.36298 | R27: =R13+R22 -> 232.36738 | S27: =S13+S22 -> 235.38121 | T27: =T13+T22 -> 238.40447 | U27: =U13+U22 -> 241.43716 | V27: =V13+V22 -> 244.47927 | W27: =W13+W22 -> 247.53081 | X27: =X13+X22 -> 250.59178 | ... AB27: =AB13+AB22 -> 262.92991 | AC27: =SUM(Q27:AB27) -> 2952.7204 | AE27: =AE13+AE22 -> 270.42403 | AF27: =AF13+AF22 -> 282.92456 | AG27: =AG13+AG22 -> 295.47176 | AH27: =AH13+AH22 -> 308.06563 | AI27: =AI13+AI22 -> 320.70616 | AJ27: =AJ13+AJ22 -> 333.39336 | AK27: =AK13+AK22 -> 346.12723 | AL27: =AL13+AL22 -> 358.90776 | ... AP27: =AP13+AP22 -> 410.49656 | AQ27: =SUM(AE27:AP27) -> 4080.3902
A30: Annahmen Conversion
A31: Bestandskunden | B31: 4000
A32: davon Abspringer | B32: 0.25
A33: Verteilung Lizenzen
A34: Teamlizenzen | B34: 0.1
A35: Einzellizenz | B35: 0.9
A37: Jahresverträge | B37: 0.99
A39: Zusatzmodule | B39: Jahr 2 | C39: Jahr 3 | D39: Jahr 2 p.M. | E39: Jahr 3 p.M.
A40: Fakturierung 2 | B40: 0.15 | C40: 0.25 | D40: =B40/12 -> 0.0125 | E40: =C40/12 -> 0.020833333
A41: Terminbuchung | B41: 0.05 | C41: 0.1 | D41: =B41/12 -> 0.0041666667 | E41: =C41/12 -> 0.0083333333
A42: Nutrishop | B42: 0.025 | C42: 0.05 | D42: =B42/12 -> 0.0020833333 | E42: =C42/12 -> 0.0041666667
A43: Weitere | B43: - | C43: 0.05 | D43: - | E43: =C43/12 -> 0.0041666667

Sheet Kosten Y 1-3
F1: Jahr 1 - Entwicklungsjahr | S1: Jahr 2 - Roll-Out | AF1: Jahr 3 - Start Expansion
A2: in TEUR | C2: FY1 | D2: FY2 | E2: FY3 | F2: Monat 1 | G2: Monat 2 | H2: Monat 3 | I2: Monat 4 | J2: Monat 5 | K2: Monat 6 | L2: Monat 7 | M2: Monat 8 | N2: Monat 9 | O2: Monat 10 | P2: Monat 11 | Q2: Monat 12 | R2: FY1 | S2: Monat 1 | T2: Monat 2 | U2: Monat 3 | V2: Monat 4 | W2: Monat 5 | X2: Monat 6 | Y2: Monat 7 | Z2: Monat 8 | AA2: Monat 9 | AB2: Monat 10 | AC2: Monat 11 | AD2: Monat 12 | AE2: FY2 | AF2: Monat 1 | AG2: Monat 2 | AH2: Monat 3 | AI2: Monat 4 | AJ2: Monat 5 | AK2: Monat 6 | AL2: Monat 7 | AM2: Monat 8 | AN2: Monat 9 | AO2: Monat 10 | AP2: Monat 11 | AQ2: Monat 12 | AR2: FY3
A3: Operations
A4: Personalkosten | C4: =R4 -> 378.7 | D4: =AE4 -> 520 | E4: =AR4 -> 696 | F4: =SUM(F5:F9) -> 30.9 | G4: =SUM(G5:G9) -> 30.9 | H4: =SUM(H5:H9) -> 30.9 | I4: =SUM(I5:I9) -> 30.9 | J4: =SUM(J5:J9) -> 30.9 | K4: =SUM(K5:K9) -> 30.9 | L4: =SUM(L5:L9) -> 30.9 | M4: =SUM(M5:M9) -> 30.9 | ... Q4: =SUM(Q5:Q9) -> 38.8 | R4: =SUM(F4:Q4) -> 378.7 | S4: =SUM(S5:S9) -> 41.5 | T4: =SUM(T5:T9) -> 41.5 | U4: =SUM(U5:U9) -> 41.5 | V4: =SUM(V5:V9) -> 41.5 | W4: =SUM(W5:W9) -> 42.5 | X4: =SUM(X5:X9) -> 42.5 | Y4: =SUM(Y5:Y9) -> 43.5 | Z4: =SUM(Z5:Z9) -> 43.5 | ... AD4: =SUM(AD5:AD9) -> 51.5 | AE4: =SUM(S4:AD4) -> 520 | AF4: =SUM(AF5:AF9) -> 53.5 | AG4: =SUM(AG5:AG9) -> 53.5 | AH4: =SUM(AH5:AH9) -> 53.5 | AI4: =SUM(AI5:AI9) -> 53.5 | AJ4: =SUM(AJ5:AJ9) -> 53.5 | AK4: =SUM(AK5:AK9) -> 53.5 | AL4: =SUM(AL5:AL9) -> 62.5 | AM4: =SUM(AM5:AM9) -> 62.5 | ... AQ4: =SUM(AQ5:AQ9) -> 62.5 | AR4: =SUM(AF4:AQ4) -> 696
A5: Geschäftsführer (MS) | C5: =R5 -> 120 | D5: =AE5 -> 138 | E5: =AR5 -> 138 | F5: 10 | G5: 10 | H5: 10 | I5: 10 | J5: 10 | K5: 10 | L5: 10 | M5: 10 | N5: 10 | O5: 10 | P5: 10 | Q5: 10 | R5: =SUM(F5:Q5) -> 120 | S5: 11.5 | T5: 11.5 | U5: 11.5 | V5: 11.5 | W5: 11.5 | X5: 11.5 | Y5: 11.5 | Z5: 11.5 | AA5: 11.5 | AB5: 11.5 | AC5: 11.5 | AD5: 11.5 | AE5: =SUM(S5:AD5) -> 138 | AF5: 11.5 | AG5: 11.5 | AH5: 11.5 | AI5: 11.5 | AJ5: 11.5 | AK5: 11.5 | AL5: 11.5 | AM5: 11.5 | AN5: 11.5 | AO5: 11.5 | AP5: 11.5 | AQ5: 11.5 | AR5: =SUM(AF5:AQ5) -> 138
A6: Mitarbeitende Operations | C6: =R6 -> 237.6 | D6: =AE6 -> 252 | E6: =AR6 -> 276 | F6: 19.8 | G6: 19.8 | H6: 19.8 | I6: 19.8 | J6: 19.8 | K6: 19.8 | L6: 19.8 | M6: 19.8 | N6: 19.8 | O6: 19.8 | P6: 19.8 | Q6: 19.8 | R6: =SUM(F6:Q6) -> 237.6 | S6: 21 | T6: 21 | U6: 21 | V6: 21 | W6: 21 | X6: 21 | Y6: 21 | Z6: 21 | AA6: 21 | AB6: 21 | AC6: 21 | AD6: 21 | AE6: =SUM(S6:AD6) -> 252 | AF6: 23 | AG6: 23 | AH6: 23 | AI6: 23 | AJ6: 23 | AK6: 23 | AL6: 23 | AM6: 23 | AN6: 23 | AO6: 23 | AP6: 23 | AQ6: 23 | AR6: =SUM(AF6:AQ6) -> 276
A7: Minijobs | C7: =R7 -> 14.1 | D7: =AE7 -> 33 | E7: =AR7 -> 60 | F7: 1.1 | G7: 1.1 | H7: 1.1 | I7: 1.1 | J7: 1.1 | K7: 1.1 | L7: 1.1 | M7: 1.1 | N7: 1.1 | O7: 1.1 | P7: 1.1 | Q7: 2 | R7: =SUM(F7:Q7) -> 14.1 | S7: 2 | T7: 2 | U7: 2 | V7: 2 | W7: 3 | X7: 3 | Y7: 3 | Z7: 3 | AA7: 3 | AB7: 3 | AC7: 3 | AD7: 4 | AE7: =SUM(S7:AD7) -> 33 | AF7: 4 | AG7: 4 | AH7: 4 | AI7: 4 | AJ7: 4 | AK7: 4 | AL7: 6 | AM7: 6 | AN7: 6 | AO7: 6 | AP7: 6 | AQ7: 6 | AR7: =SUM(AF7:AQ7) -> 60
A8: Sales Neu | C8: =R8 -> 5 | D8: =AE8 -> 66 | E8: =AR8 -> 162 | Q8: 5 | R8: =SUM(F8:Q8) -> 5 | S8: 5 | T8: 5 | U8: 5 | V8: 5 | W8: 5 | X8: 5 | Y8: 5 | Z8: 5 | AA8: 5 | AB8: 5 | AC8: 5 | AD8: 11 | AE8: =SUM(S8:AD8) -> 66 | AF8: 11 | AG8: 11 | AH8: 11 | AI8: 11 | AJ8: 11 | AK8: 11 | AL8: 16 | AM8: 16 | AN8: 16 | AO8: 16 | AP8: 16 | AQ8: 16 | AR8: =SUM(AF8:AQ8) -> 162
A9: Supporter Neu | C9: =R9 -> 2 | D9: =AE9 -> 31 | E9: =AR9 -> 60 | Q9: 2 | R9: =SUM(F9:Q9) -> 2 | S9: 2 | T9: 2 | U9: 2 | V9: 2 | W9: 2 | X9: 2 | Y9: 3 | Z9: 3 | AA9: 3 | AB9: 3 | AC9: 3 | AD9: 4 | AE9: =SUM(S9:AD9) -> 31 | AF9: 4 | AG9: 4 | AH9: 4 | AI9: 4 | AJ9: 4 | AK9: 4 | AL9: 6 | AM9: 6 | AN9: 6 | AO9: 6 | AP9: 6 | AQ9: 6 | AR9: =SUM(AF9:AQ9) -> 60
A10: SV/Lohnnebenkosten | B10: 0.23 | C10: =R10 -> 87.101 | D10: =AE10 -> 119.6 | E10: =AR10 -> 160.08 | F10: =F4*$B$10 -> 7.107 | G10: =G4*$B$10 -> 7.107 | H10: =H4*$B$10 -> 7.107 | I10: =I4*$B$10 -> 7.107 | J10: =J4*$B$10 -> 7.107 | K10: =K4*$B$10 -> 7.107 | L10: =L4*$B$10 -> 7.107 | M10: =M4*$B$10 -> 7.107 | ... Q10: =Q4*$B$10 -> 8.924 | R10: =SUM(F10:Q10) -> 87.101 | S10: =S4*$B$10 -> 9.545 | T10: =T4*$B$10 -> 9.545 | U10: =U4*$B$10 -> 9.545 | V10: =V4*$B$10 -> 9.545 | W10: =W4*$B$10 -> 9.775 | X10: =X4*$B$10 -> 9.775 | Y10: =Y4*$B$10 -> 10.005 | Z10: =Z4*$B$10 -> 10.005 | ... AD10: =AD4*$B$10 -> 11.845 | AE10: =SUM(S10:AD10) -> 119.6 | AF10: =AF4*$B$10 -> 12.305 | AG10: =AG4*$B$10 -> 12.305 | AH10: =AH4*$B$10 -> 12.305 | AI10: =AI4*$B$10 -> 12.305 | AJ10: =AJ4*$B$10 -> 12.305 | AK10: =AK4*$B$10 -> 12.305 | AL10: =AL4*$B$10 -> 14.375 | AM10: =AM4*$B$10 -> 14.375 | ... AQ10: =AQ4*$B$10 -> 14.375 | AR10: =SUM(AF10:AQ10) -> 160.08
A11: Freelancer | C11: =R11 -> 18 | D11: =AE11 -> 45 | E11: =AR11 -> 112.5 | F11: 1.5 | G11: 1.5 | H11: 1.5 | I11: 1.5 | J11: 1.5 | K11: 1.5 | L11: 1.5 | M11: 1.5 | N11: 1.5 | O11: 1.5 | P11: 1.5 | Q11: 1.5 | R11: =SUM(F11:Q11) -> 18 | S11: 2.5 | T11: 2.5 | U11: 2.5 | V11: 2.5 | W11: 2.5 | X11: 2.5 | Y11: 5 | Z11: 5 | AA11: 5 | AB11: 5 | AC11: 5 | AD11: 5 | AE11: =SUM(S11:AD11) -> 45 | AF11: 7.5 | AG11: 7.5 | AH11: 7.5 | AI11: 7.5 | AJ11: 7.5 | AK11: 7.5 | AL11: 10 | AM11: 10 | AN11: 10 | AO11: 12.5 | AP11: 12.5 | AQ11: 12.5 | AR11: =SUM(AF11:AQ11) -> 112.5
A12: Materialaufwand | C12: =R12 -> 9.6 | D12: =AE12 -> 12 | E12: =AR12 -> 45 | F12: 0.8 | G12: 0.8 | H12: 0.8 | I12: 0.8 | J12: 0.8 | K12: 0.8 | L12: 0.8 | M12: 0.8 | N12: 0.8 | O12: 0.8 | P12: 0.8 | Q12: 0.8 | R12: =SUM(F12:Q12) -> 9.6 | S12: 1 | T12: 1 | U12: 1 | V12: 1 | W12: 1 | X12: 1 | Y12: 1 | Z12: 1 | AA12: 1 | AB12: 1 | AC12: 1 | AD12: 1 | AE12: =SUM(S12:AD12) -> 12 | AF12: 2.5 | AG12: 2.5 | AH12: 2.5 | AI12: 2.5 | AJ12: 2.5 | AK12: 2.5 | AL12: 5 | AM12: 5 | AN12: 5 | AO12: 5 | AP12: 5 | AQ12: 5 | AR12: =SUM(AF12:AQ12) -> 45
A13: Raumkosten | C13: =R13 -> 9.6 | D13: =AE13 -> 14.4 | E13: =AR13 -> 33 | F13: 0.8 | G13: 0.8 | H13: 0.8 | I13: 0.8 | J13: 0.8 | K13: 0.8 | L13: 0.8 | M13: 0.8 | N13: 0.8 | O13: 0.8 | P13: 0.8 | Q13: 0.8 | R13: =SUM(F13:Q13) -> 9.6 | S13: 1.2 | T13: 1.2 | U13: 1.2 | V13: 1.2 | W13: 1.2 | X13: 1.2 | Y13: 1.2 | Z13: 1.2 | AA13: 1.2 | AB13: 1.2 | AC13: 1.2 | AD13: 1.2 | AE13: =SUM(S13:AD13) -> 14.4 | AF13: 2.5 | AG13: 2.5 | AH13: 2.5 | AI13: 2.5 | AJ13: 2.5 | AK13: 2.5 | AL13: 3 | AM13: 3 | AN13: 3 | AO13: 3 | AP13: 3 | AQ13: 3 | AR13: =SUM(AF13:AQ13) -> 33
A14: Marketing und Vertrieb | C14: =R14 -> 21 | D14: =AE14 -> 80 | E14: =AR14 -> 227.5 | F14: 1.5 | G14: 1.5 | H14: 1.5 | I14: 1.5 | J14: 1.5 | K14: 1.5 | L14: 1.5 | M14: 1.5 | N14: 1.5 | O14: 1.5 | P14: 3 | Q14: 3 | R14: =SUM(F14:Q14) -> 21 | S14: 5 | T14: 5 | U14: 5 | V14: 5 | W14: 5 | X14: 5 | Y14: 7.5 | Z14: 7.5 | AA14: 7.5 | AB14: 7.5 | AC14: 10 | AD14: 10 | AE14: =SUM(S14:AD14) -> 80 | AF14: 12.5 | AG14: 15 | AH14: 20 | AI14: 20 | AJ14: 20 | AK14: 20 | AL14: 20 | AM14: 20 | AN14: 20 | AO14: 20 | AP14: 20 | AQ14: 20 | AR14: =SUM(AF14:AQ14) -> 227.5
A15: sonstige Kosten | C15: =R15 -> 300 | D15: =AE15 -> 225 | E15: =AR15 -> 330 | F15: 25 | G15: 25 | H15: 25 | I15: 25 | J15: 25 | K15: 25 | L15: 25 | M15: 25 | N15: 25 | O15: 25 | P15: 25 | Q15: 25 | R15: =SUM(F15:Q15) -> 300 | S15: 17.5 | T15: 17.5 | U15: 17.5 | V15: 17.5 | W15: 17.5 | X15: 17.5 | Y15: 20 | Z15: 20 | AA15: 20 | AB15: 20 | AC15: 20 | AD15: 20 | AE15: =SUM(S15:AD15) -> 225 | AF15: 25 | AG15: 25 | AH15: 25 | AI15: 25 | AJ15: 25 | AK15: 25 | AL15: 30 | AM15: 30 | AN15: 30 | AO15: 30 | AP15: 30 | AQ15: 30 | AR15: =SUM(AF15:AQ15) -> 330
A16: GESAMT Operations | C16: =R16 -> 824.001 | D16: =AE16 -> 1016 | E16: =AR16 -> 1604.08 | F16: =F4+F10+F11+F12+F13+F14+F15 -> 67.607 | G16: =G4+G10+G11+G12+G13+G14+G15 -> 67.607 | H16: =H4+H10+H11+H12+H13+H14+H15 -> 67.607 | I16: =I4+I10+I11+I12+I13+I14+I15 -> 67.607 | J16: =J4+J10+J11+J12+J13+J14+J15 -> 67.607 | K16: =K4+K10+K11+K12+K13+K14+K15 -> 67.607 | L16: =L4+L10+L11+L12+L13+L14+L15 -> 67.607 | M16: =M4+M10+M11+M12+M13+M14+M15 -> 67.607 | ... Q16: =Q4+Q10+Q11+Q12+Q13+Q14+Q15 -> 78.824 | R16: =SUM(F16:Q16) -> 824.001 | S16: =S4+S10+S11+S12+S13+S14+S15 -> 78.245 | T16: =T4+T10+T11+T12+T13+T14+T15 -> 78.245 | U16: =U4+U10+U11+U12+U13+U14+U15 -> 78.245 | V16: =V4+V10+V11+V12+V13+V14+V15 -> 78.245 | W16: =W4+W10+W11+W12+W13+W14+W15 -> 79.475 | X16: =X4+X10+X11+X12+X13+X14+X15 -> 79.475 | Y16: =Y4+Y10+Y11+Y12+Y13+Y14+Y15 -> 88.205 | Z16: =Z4+Z10+Z11+Z12+Z13+Z14+Z15 -> 88.205 | ... AD16: =AD4+AD10+AD11+AD12+AD13+AD14+AD15 -> 100.545 | AE16: =SUM(S16:AD16) -> 1016 | AF16: =AF4+AF10+AF11+AF12+AF13+AF14+AF15 -> 115.805 | AG16: =AG4+AG10+AG11+AG12+AG13+AG14+AG15 -> 118.305 | AH16: =AH4+AH10+AH11+AH12+AH13+AH14+AH15 -> 123.305 | AI16: =AI4+AI10+AI11+AI12+AI13+AI14+AI15 -> 123.305 | AJ16: =AJ4+AJ10+AJ11+AJ12+AJ13+AJ14+AJ15 -> 123.305 | AK16: =AK4+AK10+AK11+AK12+AK13+AK14+AK15 -> 123.305 | AL16: =AL4+AL10+AL11+AL12+AL13+AL14+AL15 -> 144.875 | AM16: =AM4+AM10+AM11+AM12+AM13+AM14+AM15 -> 144.875 | ... AQ16: =AQ4+AQ10+AQ11+AQ12+AQ13+AQ14+AQ15 -> 147.375 | AR16: =SUM(AF16:AQ16) -> 1604.08
A18: Entwicklung
A19: Personalkosten | C19: =R19 -> 174 | D19: =AE19 -> 318 | E19: =AR19 -> 402 | F19: =SUM(F20:F21) -> 14.5 | G19: =SUM(G20:G21) -> 14.5 | H19: =SUM(H20:H21) -> 14.5 | I19: =SUM(I20:I21) -> 14.5 | J19: =SUM(J20:J21) -> 14.5 | K19: =SUM(K20:K21) -> 14.5 | L19: =SUM(L20:L21) -> 14.5 | M19: =SUM(M20:M21) -> 14.5 | ... Q19: =SUM(Q20:Q21) -> 14.5 | R19: =SUM(F19:Q19) -> 174 | S19: =SUM(S20:S21) -> 23 | T19: =SUM(T20:T21) -> 23 | U19: =SUM(U20:U21) -> 23 | V19: =SUM(V20:V21) -> 23 | W19: =SUM(W20:W21) -> 23 | X19: =SUM(X20:X21) -> 23 | Y19: =SUM(Y20:Y21) -> 30 | Z19: =SUM(Z20:Z21) -> 30 | ... AD19: =SUM(AD20:AD21) -> 30 | AE19: =SUM(S19:AD19) -> 318 | AF19: =SUM(AF20:AF21) -> 30 | AG19: =SUM(AG20:AG21) -> 30 | AH19: =SUM(AH20:AH21) -> 30 | AI19: =SUM(AI20:AI21) -> 30 | AJ19: =SUM(AJ20:AJ21) -> 30 | AK19: =SUM(AK20:AK21) -> 30 | AL19: =SUM(AL20:AL21) -> 37 | AM19: =SUM(AM20:AM21) -> 37 | ... AQ19: =SUM(AQ20:AQ21) -> 37 | AR19: =SUM(AF19:AQ19) -> 402
A20: Leitung Entwicklung (TR) | C20: =R20 -> 90 | D20: =AE20 -> 108 | E20: =AR20 -> 108 | F20: 7.5 | G20: 7.5 | H20: 7.5 | I20: 7.5 | J20: 7.5 | K20: 7.5 | L20: 7.5 | M20: 7.5 | N20: 7.5 | O20: 7.5 | P20: 7.5 | Q20: 7.5 | R20: =SUM(F20:Q20) -> 90 | S20: 9 | T20: 9 | U20: 9 | V20: 9 | W20: 9 | X20: 9 | Y20: 9 | Z20: 9 | AA20: 9 | AB20: 9 | AC20: 9 | AD20: 9 | AE20: =SUM(S20:AD20) -> 108 | AF20: 9 | AG20: 9 | AH20: 9 | AI20: 9 | AJ20: 9 | AK20: 9 | AL20: 9 | AM20: 9 | AN20: 9 | AO20: 9 | AP20: 9 | AQ20: 9 | AR20: =SUM(AF20:AQ20) -> 108
A21: Fullstack Developer | C21: =R21 -> 84 | D21: =AE21 -> 210 | E21: =AR21 -> 294 | F21: 7 | G21: 7 | H21: 7 | I21: 7 | J21: 7 | K21: 7 | L21: 7 | M21: 7 | N21: 7 | O21: 7 | P21: 7 | Q21: 7 | R21: =SUM(F21:Q21) -> 84 | S21: 14 | T21: 14 | U21: 14 | V21: 14 | W21: 14 | X21: 14 | Y21: 21 | Z21: 21 | AA21: 21 | AB21: 21 | AC21: 21 | AD21: 21 | AE21: =SUM(S21:AD21) -> 210 | AF21: 21 | AG21: 21 | AH21: 21 | AI21: 21 | AJ21: 21 | AK21: 21 | AL21: 28 | AM21: 28 | AN21: 28 | AO21: 28 | AP21: 28 | AQ21: 28 | AR21: =SUM(AF21:AQ21) -> 294
A22: SV/Lohnnebenkosten | C22: =R22 -> 40.02 | D22: =AE22 -> 73.14 | E22: =AR22 -> 92.46 | F22: =F19*$B$10 -> 3.335 | G22: =G19*$B$10 -> 3.335 | H22: =H19*$B$10 -> 3.335 | I22: =I19*$B$10 -> 3.335 | J22: =J19*$B$10 -> 3.335 | K22: =K19*$B$10 -> 3.335 | L22: =L19*$B$10 -> 3.335 | M22: =M19*$B$10 -> 3.335 | ... Q22: =Q19*$B$10 -> 3.335 | R22: =SUM(F22:Q22) -> 40.02 | S22: =S19*$B$10 -> 5.29 | T22: =T19*$B$10 -> 5.29 | U22: =U19*$B$10 -> 5.29 | V22: =V19*$B$10 -> 5.29 | W22: =W19*$B$10 -> 5.29 | X22: =X19*$B$10 -> 5.29 | Y22: =Y19*$B$10 -> 6.9 | Z22: =Z19*$B$10 -> 6.9 | ... AD22: =AD19*$B$10 -> 6.9 | AE22: =SUM(S22:AD22) -> 73.14 | AF22: 6.9 | AG22: =AG19*$B$10 -> 6.9 | AH22: =AH19*$B$10 -> 6.9 | AI22: =AI19*$B$10 -> 6.9 | AJ22: =AJ19*$B$10 -> 6.9 | AK22: =AK19*$B$10 -> 6.9 | AL22: =AL19*$B$10 -> 8.51 | AM22: =AM19*$B$10 -> 8.51 | AN22: =AN19*$B$10 -> 8.51 | ... AQ22: =AQ19*$B$10 -> 8.51 | AR22: =SUM(AF22:AQ22) -> 92.46
A23: Freelancer | C23: =R23 -> 30 | D23: =AE23 -> 45 | E23: =AR23 -> 90 | F23: 5 | G23: 5 | H23: 5 | I23: 3 | J23: 3 | K23: 3 | L23: 2 | M23: 2 | N23: 2 | O23: 0 | P23: 0 | Q23: 0 | R23: =SUM(F23:Q23) -> 30 | S23: 2.5 | T23: 2.5 | U23: 2.5 | V23: 2.5 | W23: 2.5 | X23: 2.5 | Y23: 5 | Z23: 5 | AA23: 5 | AB23: 5 | AC23: 5 | AD23: 5 | AE23: =SUM(S23:AD23) -> 45 | AF23: 7.5 | AG23: 7.5 | AH23: 7.5 | AI23: 7.5 | AJ23: 7.5 | AK23: 7.5 | AL23: 7.5 | AM23: 7.5 | AN23: 7.5 | AO23: 7.5 | AP23: 7.5 | AQ23: 7.5 | AR23: =SUM(AF23:AQ23) -> 90
A24: Materialaufwand | C24: =R24 -> 6 | D24: =AE24 -> 6 | E24: =AR24 -> 12 | F24: 0.5 | G24: 0.5 | H24: 0.5 | I24: 0.5 | J24: 0.5 | K24: 0.5 | L24: 0.5 | M24: 0.5 | N24: 0.5 | O24: 0.5 | P24: 0.5 | Q24: 0.5 | R24: =SUM(F24:Q24) -> 6 | S24: 0.5 | T24: 0.5 | U24: 0.5 | V24: 0.5 | W24: 0.5 | X24: 0.5 | Y24: 0.5 | Z24: 0.5 | AA24: 0.5 | AB24: 0.5 | AC24: 0.5 | AD24: 0.5 | AE24: =SUM(S24:AD24) -> 6 | AF24: 1 | AG24: 1 | AH24: 1 | AI24: 1 | AJ24: 1 | AK24: 1 | AL24: 1 | AM24: 1 | AN24: 1 | AO24: 1 | AP24: 1 | AQ24: 1 | AR24: =SUM(AF24:AQ24) -> 12
A25: IT | C25: =R25 -> 1 | D25: =AE25 -> 12 | E25: =AR25 -> 12 | F25: 1 | G25: =SUM(G26:G27) -> 0 | H25: =SUM(H26:H27) -> 0 | I25: =SUM(I26:I27) -> 0 | J25: =SUM(J26:J27) -> 0 | K25: =SUM(K26:K27) -> 0 | L25: =SUM(L26:L27) -> 0 | M25: =SUM(M26:M27) -> 0 | N25: =SUM(N26:N27) -> 0 | ... P25: =SUM(P26:P27) -> 0 | Q25: 0 | R25: =SUM(F25:Q25) -> 1 | S25: 1 | T25: =SUM(T26:T27) -> 1 | U25: =SUM(U26:U27) -> 1 | V25: =SUM(V26:V27) -> 1 | W25: =SUM(W26:W27) -> 1 | X25: =SUM(X26:X27) -> 1 | Y25: =SUM(Y26:Y27) -> 1 | Z25: =SUM(Z26:Z27) -> 1 | AA25: =SUM(AA26:AA27) -> 1 | ... AD25: =SUM(AD26:AD27) -> 1 | AE25: =SUM(S25:AD25) -> 12 | AF25: 1 | AG25: =SUM(AG26:AG27) -> 1 | AH25: =SUM(AH26:AH27) -> 1 | AI25: =SUM(AI26:AI27) -> 1 | AJ25: =SUM(AJ26:AJ27) -> 1 | AK25: =SUM(AK26:AK27) -> 1 | AL25: =SUM(AL26:AL27) -> 1 | AM25: =SUM(AM26:AM27) -> 1 | AN25: =SUM(AN26:AN27) -> 1 | ... AQ25: =SUM(AQ26:AQ27) -> 1 | AR25: =SUM(AF25:AQ25) -> 12
A26: Hardware | C26: =R26 -> 5 | D26: =AE26 -> 5 | E26: =AR26 -> 10 | F26: 0 | G26: 0 | H26: 0 | I26: 0 | J26: 0 | K26: 0 | L26: 0 | M26: 0 | N26: 0 | O26: 0 | P26: 0 | Q26: 5 | R26: =SUM(F26:Q26) -> 5 | S26: 5 | T26: 0 | U26: 0 | V26: 0 | W26: 0 | X26: 0 | Y26: 0 | Z26: 0 | AA26: 0 | AB26: 0 | AC26: 0 | AD26: 0 | AE26: =SUM(S26:AD26) -> 5 | AF26: 10 | AG26: 0 | AH26: 0 | AI26: 0 | AJ26: 0 | AK26: 0 | AL26: 0 | AM26: 0 | AN26: 0 | AO26: 0 | AP26: 0 | AQ26: 0 | AR26: =SUM(AF26:AQ26) -> 10
A27: Lizenzen/Entwicklungsumgebung | C27: =R27 -> 0 | D27: =AE27 -> 12 | E27: =AR27 -> 12 | F27: 0 | G27: 0 | H27: 0 | I27: 0 | J27: 0 | K27: 0 | L27: 0 | M27: 0 | N27: 0 | O27: 0 | P27: 0 | Q27: 0 | R27: =SUM(F27:Q27) -> 0 | S27: 1 | T27: 1 | U27: 1 | V27: 1 | W27: 1 | X27: 1 | Y27: 1 | Z27: 1 | AA27: 1 | AB27: 1 | AC27: 1 | AD27: 1 | AE27: =SUM(S27:AD27) -> 12 | AF27: 1 | AG27: 1 | AH27: 1 | AI27: 1 | AJ27: 1 | AK27: 1 | AL27: 1 | AM27: 1 | AN27: 1 | AO27: 1 | AP27: 1 | AQ27: 1 | AR27: =SUM(AF27:AQ27) -> 12
A29: Design/UI/UX, Agenturen | C29: =R29 -> 0 | D29: =AE29 -> 30 | E29: =AR29 -> 92.5 | F29: 0 | G29: 0 | H29: 0 | I29: 0 | J29: 0 | K29: 0 | L29: 0 | M29: 0 | N29: 0 | O29: 0 | P29: 0 | Q29: 0 | R29: =SUM(F29:Q29) -> 0 | S29: 2.5 | T29: 2.5 | U29: 2.5 | V29: 2.5 | W29: 2.5 | X29: 2.5 | Y29: 2.5 | Z29: 2.5 | AA29: 2.5 | AB29: 2.5 | AC29: 2.5 | AD29: 2.5 | AE29: =SUM(S29:AD29) -> 30 | AF29: 5 | AG29: 5 | AH29: 5 | AI29: 7.5 | AJ29: 7.5 | AK29: 7.5 | AL29: 7.5 | AM29: 7.5 | AN29: 10 | AO29: 10 | AP29: 10 | AQ29: 10 | AR29: =SUM(AF29:AQ29) -> 92.5
E30: =AR30 -> 0
A31: Beratungen (Legal etc.) | C31: =R31 -> 8 | D31: =AE31 -> 15 | E31: =AR31 -> 35 | F31: 5 | G31: 0 | H31: 0 | I31: 2 | J31: 0 | K31: 0 | L31: 0 | M31: 0 | N31: 0 | O31: 1 | P31: 0 | Q31: 0 | R31: =SUM(F31:Q31) -> 8 | S31: 5 | T31: 0 | U31: 0 | V31: 2.5 | W31: 0 | X31: 0 | Y31: 5 | Z31: 0 | AA31: 0 | AB31: 2.5 | AC31: 0 | AD31: 0 | AE31: =SUM(S31:AD31) -> 15 | AF31: 5 | AG31: 5 | AH31: 5 | AI31: 0 | AJ31: 0 | AK31: 5 | AL31: 5 | AM31: 0 | AN31: 0 | AO31: 5 | AP31: 5 | AQ31: 0 | AR31: =SUM(AF31:AQ31) -> 35
A32: Gesamt Entwicklung | C32: =R32 -> 259.02 | D32: =AE32 -> 499.14 | E32: =AR32 -> 735.96 | F32: =F19+F22+F23+F24+F25+F29+F31 -> 29.335 | G32: =G19+G22+G23+G24+G25+G29+G31 -> 23.335 | H32: =H19+H22+H23+H24+H25+H29+H31 -> 23.335 | I32: =I19+I22+I23+I24+I25+I29+I31 -> 23.335 | J32: =J19+J22+J23+J24+J25+J29+J31 -> 21.335 | K32: =K19+K22+K23+K24+K25+K29+K31 -> 21.335 | L32: =L19+L22+L23+L24+L25+L29+L31 -> 20.335 | M32: =M19+M22+M23+M24+M25+M29+M31 -> 20.335 | ... Q32: =Q19+Q22+Q23+Q24+Q25+Q29+Q31 -> 18.335 | R32: =SUM(F32:Q32) -> 259.02 | S32: =S19+S22+S23+S24+S25+S29+S31 -> 39.79 | T32: =T19+T22+T23+T24+T25+T29+T31 -> 34.79 | U32: =U19+U22+U23+U24+U25+U29+U31 -> 34.79 | V32: =V19+V22+V23+V24+V25+V29+V31 -> 37.29 | W32: =W19+W22+W23+W24+W25+W29+W31 -> 34.79 | X32: =X19+X22+X23+X24+X25+X29+X31 -> 34.79 | Y32: =Y19+Y22+Y23+Y24+Y25+Y29+Y31 -> 50.9 | Z32: =Z19+Z22+Z23+Z24+Z25+Z29+Z31 -> 45.9 | ... AD32: =AD19+AD22+AD23+AD24+AD25+AD29+AD31 -> 45.9 | AE32: =SUM(S32:AD32) -> 499.14 | AF32: =AF19+AF22+AF23+AF24+AF25+AF29+AF31 -> 56.4 | AG32: =AG19+AG22+AG23+AG24+AG25+AG29+AG31 -> 56.4 | AH32: =AH19+AH22+AH23+AH24+AH25+AH29+AH31 -> 56.4 | AI32: =AI19+AI22+AI23+AI24+AI25+AI29+AI31 -> 53.9 | AJ32: =AJ19+AJ22+AJ23+AJ24+AJ25+AJ29+AJ31 -> 53.9 | AK32: =AK19+AK22+AK23+AK24+AK25+AK29+AK31 -> 58.9 | AL32: =AL19+AL22+AL23+AL24+AL25+AL29+AL31 -> 67.51 | AM32: =AM19+AM22+AM23+AM24+AM25+AM29+AM31 -> 62.51 | ... AQ32: =AQ19+AQ22+AQ23+AQ24+AQ25+AQ29+AQ31 -> 65.01 | AR32: =SUM(AF32:AQ32) -> 735.96
A34: Abschreibungen | C34: =R34 -> 6 | D34: =AE34 -> 42 | E34: =AR34 -> 42 | F34: 0.5 | G34: 0.5 | H34: 0.5 | I34: 0.5 | J34: 0.5 | K34: 0.5 | L34: 0.5 | M34: 0.5 | N34: 0.5 | O34: 0.5 | P34: 0.5 | Q34: 0.5 | R34: =SUM(F34:Q34) -> 6 | S34: 3.5 | T34: 3.5 | U34: 3.5 | V34: 3.5 | W34: 3.5 | X34: 3.5 | Y34: 3.5 | Z34: 3.5 | AA34: 3.5 | AB34: 3.5 | AC34: 3.5 | AD34: 3.5 | AE34: =SUM(S34:AD34) -> 42 | AF34: 3.5 | AG34: 3.5 | AH34: 3.5 | AI34: 3.5 | AJ34: 3.5 | AK34: 3.5 | AL34: 3.5 | AM34: 3.5 | AN34: 3.5 | AO34: 3.5 | AP34: 3.5 | AQ34: 3.5 | AR34: =SUM(AF34:AQ34) -> 42
A36: GESAMT Kosten | C36: =C16+C32+C34 -> 1089.021 | D36: =D16+D32+D34 -> 1557.14 | E36: =E16+E32+E34 -> 2382.04 | F36: =F16+F32+F34 -> 97.442 | G36: =G16+G32+G34 -> 91.442 | H36: =H16+H32+H34 -> 91.442 | I36: =I16+I32+I34 -> 91.442 | J36: =J16+J32+J34 -> 89.442 | ... Q36: =Q16+Q32+Q34 -> 97.659 | R36: =SUM(F36:Q36) -> 1089.021 | S36: =S16+S32+S34 -> 121.535 | T36: =T16+T32+T34 -> 116.535 | U36: =U16+U32+U34 -> 116.535 | V36: =V16+V32+V34 -> 119.035 | W36: =W16+W32+W34 -> 117.765 | X36: =X16+X32+X34 -> 117.765 | Y36: =Y16+Y32+Y34 -> 142.605 | Z36: =Z16+Z32+Z34 -> 137.605 | ... AR36: =AR16+AR32+AR34 -> 2382.04
